yuconv/__init__.py
yuconv/__main__.py
yuconv/converter.py
yuconv/text_cleaner.py
yuconv/transliteration.py
yuconv/yu_converter.py
yuconv-0.3.dist-info/licenses/LICENSE
yuconv-0.3.dist-info/METADATA
yuconv-0.3.dist-info/WHEEL
yuconv-0.3.dist-info/entry_points.txt
yuconv-0.3.dist-info/top_level.txt
yuconv-0.3.dist-info/RECORD
