Metadata-Version: 2.4
Name: yuconv
Version: 0.3
Summary: YuConv is very simple transliteration tool for Serbian language for Cyrillic2Latin and Latin2Cyrillic transliteration.
Home-page: https://github.com/DarkoMilosevic86/yuconv.git
Author: Darko Milosevic
Author-email: daremc86@gmail.com
Classifier: Programming Language :: Python :: 3
Classifier: License :: OSI Approved :: GNU General Public License v3 (GPLv3)
Classifier: Operating System :: OS Independent
Requires-Python: >=3.6
License-File: LICENSE
Requires-Dist: python-docx
Dynamic: author
Dynamic: author-email
Dynamic: classifier
Dynamic: description
Dynamic: description-content-type
Dynamic: home-page
Dynamic: license-file
Dynamic: requires-dist
Dynamic: requires-python
Dynamic: summary
